bm3dornl/__init__.py
bm3dornl/bm3d.py
bm3dornl/bm3d_rust.cpython-38-x86_64-linux-gnu.so
bm3dornl/fourier_svd.py
bm3dornl/phantom.py
bm3dornl/plot.py
bm3dornl/utils.py
bm3dornl-0.7.1.dist-info/METADATA
bm3dornl-0.7.1.dist-info/WHEEL
bm3dornl-0.7.1.dist-info/licenses/LICENSE
bm3dornl-0.7.1.dist-info/RECORD
