Metadata-Version: 2.4
Name: bm3dornl
Version: 0.7.1
Requires-Dist: numpy
Requires-Dist: scipy
Requires-Dist: scikit-image
Requires-Dist: bm3dornl-gui==0.7.1 ; extra == 'gui'
Provides-Extra: gui
License-File: LICENSE
Summary: BM3D for streak artifact removal in neutron imaging
Keywords: BM3D,image processing,neutron imaging,denoising,tomography,ring artifacts,Rust
License-Expression: MIT
Requires-Python: >=3.12
Project-URL: documentation, https://bm3dornl.readthedocs.io/en/latest/
Project-URL: homepage, https://github.com/ornlneutronimaging/bm3dornl
Project-URL: issues, https://github.com/ornlneutronimaging/bm3dornl/issues
Project-URL: repository, https://github.com/ornlneutronimaging/bm3dornl
